pystream/__init__.py
pystream/logger.py
pystream/main.py
pystream/requirements.txt
pystream/utils.py
pystream/models/authenticator.py
pystream/models/config.py
pystream/models/images.py
pystream/models/secure.py
pystream/models/squire.py
pystream/models/stream.py
pystream/models/subtitles.py
pystream/routers/auth.py
pystream/routers/basics.py
pystream/routers/blank.jpg
pystream/routers/video.py
pystream/templates/index.html
pystream/templates/land.html
pystream/templates/list.html
pystream/templates/logout.html
pystream/templates/session.html
pystream/templates/unauthorized.html
stream_localhost-2.1.dist-info/LICENSE
stream_localhost-2.1.dist-info/METADATA
stream_localhost-2.1.dist-info/WHEEL
stream_localhost-2.1.dist-info/top_level.txt
stream_localhost-2.1.dist-info/RECORD
