Metadata-Version: 2.1
Name: stream-localhost
Version: 2.1
Summary: Python module to, stream videos via authenticated sessions using FastAPI
Author-email: Vignesh Rao <svignesh1793@gmail.com>
License: MIT License
Project-URL: Homepage, https://github.com/thevickypedia/pystream
Project-URL: Docs, https://thevickypedia.github.io/PyStream/
Project-URL: Source, https://github.com/thevickypedia/pystream
Project-URL: Bug Tracker, https://github.com/thevickypedia/pystream/issues
Project-URL: Release Notes, https://github.com/thevickypedia/pystream/blob/main/release_notes.rst
Keywords: video-streaming,localhost
Classifier: Development Status :: 5 - Production/Stable
Classifier: Intended Audience :: Information Technology
Classifier: License :: OSI Approved :: MIT License
Classifier: Operating System :: OS Independent
Classifier: Programming Language :: Python :: 3.8
Classifier: Programming Language :: Python :: 3.9
Classifier: Programming Language :: Python :: 3.10
Classifier: Programming Language :: Python :: 3.11
Classifier: Topic :: Multimedia :: Video
Requires-Python: >=3.8
License-File: LICENSE
Requires-Dist: aiofiles ==23.2.1
Requires-Dist: cryptography ==42.0.1
Requires-Dist: fastapi ==0.109.0
Requires-Dist: itsdangerous ==2.1.2
Requires-Dist: Jinja2 ==3.1.3
Requires-Dist: opencv-python ==4.9.0.80
Requires-Dist: pydantic ==2.5.3
Requires-Dist: pydantic-settings ==2.1.0
Requires-Dist: python-multipart ==0.0.6
Requires-Dist: requests ==2.31.0
Requires-Dist: uvicorn ==0.27.0
Requires-Dist: websockets ==12.0
Provides-Extra: dev
Requires-Dist: sphinx ==5.1.1 ; extra == 'dev'
Requires-Dist: pre-commit ; extra == 'dev'
Requires-Dist: recommonmark ; extra == 'dev'
Requires-Dist: gitverse ; extra == 'dev'
